strobesbufs/__init__.py
strobesbufs/__version__.py
strobesbufs/analyzers/__init__.py
strobesbufs/analyzers/analyzers_pb2.py
strobesbufs/analyzers/analyzers_service_pb2.py
strobesbufs/analyzers/analyzers_service_pb2_grpc.py
strobesbufs/analyzers/enums.py
strobesbufs/analyzers/proto_wrapper.py
strobesbufs/canis/__init__.py
strobesbufs/canis/canis_pb2.py
strobesbufs/canis/canis_pb2_grpc.py
strobesbufs/messier/__init__.py
strobesbufs/messier/common_pb2.py
strobesbufs/messier/analyzers/__init__.py
strobesbufs/messier/analyzers/analyzer_pb2.py
strobesbufs/messier/analyzers/bandit_pb2.py
strobesbufs/messier/analyzers/naabu_pb2.py
strobesbufs/messier/analyzers/subfinder_pb2.py
strobesbufs/messier/analyzers/wappalyzer_pb2.py
strobesbufs/messier/functions/__init__.py
strobesbufs/messier/functions/docker_pb2.py
strobesbufs/messier/functions/function_pb2.py
strobesbufs/messier/functions/git_pb2.py
strobesbufs/messier/functions/slack_pb2.py
strobesbufs/messier/functions/svn_pb2.py
strobesbufs/messier/tasks/__init__.py
strobesbufs/messier/tasks/task_pb2.py
strobesbufs/messier/workflows/__init__.py
strobesbufs/messier/workflows/services_pb2.py
strobesbufs/messier/workflows/services_pb2_grpc.py
strobesbufs/messier/workflows/workflow_pb2.py
strobesbufs/scrappers/__init__.py
strobesbufs/scrappers/alienvault_pb2.py
strobesbufs/scrappers/debian_pb2.py
strobesbufs/scrappers/exploitdb_pb2.py
strobesbufs/scrappers/msbulletin_pb2.py
strobesbufs/scrappers/nodejs_pb2.py
strobesbufs/scrappers/nvd_pb2.py
strobesbufs/scrappers/oval_ubuntu_pb2.py
strobesbufs/scrappers/packet_storm_pb2.py
strobesbufs/scrappers/photon_pb2.py
strobesbufs/scrappers/php_security_pb2.py
strobesbufs/scrappers/python_pb2.py
strobesbufs/scrappers/redhat_pb2.py
strobesbufs/scrappers/ruby_pb2.py
strobesbufs/scrappers/rust_pb2.py
strobesbufs/scrappers/talos_pb2.py
strobesbufs/scrappers/xogoogle_pb2.py
strobesbufs/scrappers/xotweet_pb2.py
Strobesbufs-0.0.299.dist-info/LICENSE
Strobesbufs-0.0.299.dist-info/METADATA
Strobesbufs-0.0.299.dist-info/WHEEL
Strobesbufs-0.0.299.dist-info/top_level.txt
Strobesbufs-0.0.299.dist-info/RECORD
