Metadata-Version: 2.1
Name: Strobesbufs
Version: 0.0.299
Summary: Contains all the protos created by strobesbuf as a package to use
Home-page: https://github.com/strobes-co/strobesbufs-py
Author: Akhil Reni
Author-email: akhil@wesecureapp.com
License: GPLv3
Platform: UNKNOWN
Requires-Python: >=3.6
Requires-Dist: grpcio (==1.30.0)
Requires-Dist: grpcio-tools (==1.30.0)
